[{"regNum":"564BDC","brand":"BMW","model":"M3","speed":230,"category":"Sport","registered":false},{"regNum":"BBB222","brand":"Volvo","model":"C70","speed":230,"category":"Sport","registered":false},{"regNum":"DEF789","brand":"Mercedes","model":"SL900","speed":250,"category":"Saloon","registered":false},{"regNum":"MAZ006","brand":"Mazda","model":"2.0 SE-L","speed":208,"category":"Saloon","registered":false},{"regNum":"MER134","brand":"Mercedes","model":"E200d SE Premium","speed":224,"category":"Saloon","registered":false},{"regNum":"MLJ531","brand":"BMW","model":"M6","speed":250,"category":"Hatchback","registered":false},{"regNum":"PEG208","brand":"Peugeot","model":"208 Hatchback","speed":175,"category":"Sport","registered":false}]